LICENSE.txt
setup.cfg
setup.py
accounts/__init__.py
accounts/metadata.py
accounts/runtime.py
accounts/utility.py
tests/test_calendar.py
tests/test_config.py
tests/test_configuration.py
tests/test_loanGiven.py
tests/test_rate_type.py
tests/test_runtime.py
tests/test_schedule.py
transaction_accounts.egg-info/PKG-INFO
transaction_accounts.egg-info/SOURCES.txt
transaction_accounts.egg-info/dependency_links.txt
transaction_accounts.egg-info/requires.txt
transaction_accounts.egg-info/top_level.txt