Metadata-Version: 2.1
Name: transaction-accounts
Version: 0.2.1
Summary: Create configuration for transactional accounts and implement account runtime
Home-page: https://github.com/igormusic/transaction-accounts
Download-URL: https://github.com/igormusic/transaction-accounts/archive/refs/tags/0.0.6.tar.gz
Author: Igor Music
Author-email: igormusich@gmail.com
License: MIT
Keywords: TRANSACTION PROCESSING,LOANS,SAVINGS,ACCOUNTS,FINANCE,BANKING
Classifier: Development Status :: 4 - Beta
Classifier: Intended Audience :: Developers
Classifier: Topic :: Software Development :: Build Tools
Classifier: License :: OSI Approved :: MIT License
Classifier: Programming Language :: Python :: 3.9
License-File: LICENSE.txt
